creator/__init__.py
creator/input.py
creator/embed_creator/__init__.py
creator/embed_creator/methods.py
creator_yaap/__init__.py
creator_yaap/input.py
creator_yaap/embed_creator/__init__.py
creator_yaap/embed_creator/methods.py
embedcreator_yaap-0.0.4.dist-info/LICENSE
embedcreator_yaap-0.0.4.dist-info/METADATA
embedcreator_yaap-0.0.4.dist-info/WHEEL
embedcreator_yaap-0.0.4.dist-info/top_level.txt
embedcreator_yaap-0.0.4.dist-info/RECORD
