Metadata-Version: 2.2
Name: embedcreator-yaap
Version: 0.0.4
Author: Leticia Sousa
Author-email: leticialimasousa2007@gmail.com
License: MIT License
License-File: LICENSE
Requires-Dist: discord.py
Dynamic: author
Dynamic: author-email
Dynamic: description
Dynamic: description-content-type
Dynamic: license
Dynamic: requires-dist
